xivapi2/__init__.py
xivapi2/client.py
xivapi2/errors.py
xivapi2/models.py
xivapi2/py.typed
xivapi2/query.py
xivapi2/utils.py
xivapi2-0.1.0b1.dist-info/METADATA
xivapi2-0.1.0b1.dist-info/WHEEL
xivapi2-0.1.0b1.dist-info/licenses/LICENSE
xivapi2-0.1.0b1.dist-info/RECORD
