Metadata-Version: 2.4
Name: xivapi2
Version: 0.1.0b1
Summary: An unofficial asynchronous Python library for xivapi.
Project-URL: Homepage, https://github.com/RikuPy/xivapi2
Project-URL: Issues, https://github.com/RikuPy/xivapi2/issues
Author: RikuPy
License-Expression: MIT
License-File: LICENSE
Classifier: Development Status :: 4 - Beta
Classifier: Intended Audience :: Developers
Classifier: License :: OSI Approved :: MIT License
Classifier: Programming Language :: Python :: 3
Classifier: Programming Language :: Python :: 3.12
Classifier: Programming Language :: Python :: 3.13
Classifier: Topic :: Games/Entertainment
Classifier: Topic :: Software Development :: Libraries
Classifier: Topic :: Software Development :: Libraries :: Python Modules
Classifier: Typing :: Typed
Requires-Python: >=3.12
Requires-Dist: aiohttp>=3.11.16
